levenshtein_matching-0.5.2.dist-info/METADATA
levenshtein_matching-0.5.2.dist-info/WHEEL
levenshtein_matching/__init__.py
levenshtein_matching/levenshtein_matching.cpython-312-x86_64-linux-gnu.so
levenshtein_matching-0.5.2.dist-info/RECORD
