Metadata-Version: 2.3
Name: levenshtein_matching
Version: 0.5.2
Classifier: Programming Language :: Rust
Classifier: Programming Language :: Python :: Implementation :: CPython
Classifier: Programming Language :: Python :: Implementation :: PyPy
Summary: A library for string matching between two lists.
Author: Benjamin Chandler
Requires-Python: >=3.8
